drf_simple_api_key_auth/__init__.py
drf_simple_api_key_auth/authentication.py
drf_simple_api_key_auth/settings.py
drf_simple_api_key_auth-0.1.0.dist-info/DESCRIPTION.rst
drf_simple_api_key_auth-0.1.0.dist-info/METADATA
drf_simple_api_key_auth-0.1.0.dist-info/RECORD
drf_simple_api_key_auth-0.1.0.dist-info/WHEEL
drf_simple_api_key_auth-0.1.0.dist-info/metadata.json
drf_simple_api_key_auth-0.1.0.dist-info/pbr.json
drf_simple_api_key_auth-0.1.0.dist-info/top_level.txt
