Metadata-Version: 2.0
Name: drf-simple-api-key-auth
Version: 0.1.0
Summary: Simple API key auth for Django REST Framework
Home-page: https://github.com/ArtProcessors/drf-simple-api-key-auth
Author: Art Processors
Author-email: jacob@artprocessors.net
License: UNKNOWN
Platform: UNKNOWN
Requires-Dist: django
